[{"id":100140006,"ko":"엘레멘탈 소드","jp":"エレメンタルソード","icon":"WP_Sword_G4_006.png","top":["8,0.7271%,10-1","9,0.4269%,10-2"]},{"id":100130001,"ko":"시르 블레이드","jp":"シルーブレード","icon":"WP_Sword_G3_001.png","top":["0,0.3880%,10-2","8,1.8676%,10-5","7,0.3880%,10-2"]},{"id":100130005,"ko":"가디언스 소드","jp":"ガーディアンズソード","icon":"WP_Sword_G3_005.png","top":["0,1.1640%,10-3","7,1.1640%,10-3"]},{"id":200130004,"ko":"다크 크리스탈 흉갑","jp":"ダーククリスタルアーマー","icon":"AR_Torso_G3_002.png","top":["7,3.2641%,10-4","0,0.8127%,10-1","5,0.8127%,10-1"]},{"id":100140008,"ko":"스피릿츠 소드","jp":"スピリッツ·ソード","icon":"WP_Sword_G4_008.png","top":["8,0.7271%,10-1","9,0.4269%,10-2"]},{"id":200130005,"ko":"마제스틱 로브","jp":"マジェスティックローブ","icon":"AR_Torso_G3_001.png","top":["7,3.2641%,10-4","0,0.8127%,10-1","5,0.8127%,10-1"]},{"id":100130004,"ko":"소드 오브 발할라","jp":"ソード·オブ·ヴァルハラ","icon":"WP_Sword_G3_004.png","top":["8,1.8676%,10-5","0,0.3880%,10-2","7,0.3880%,10-2"]},{"id":100240005,"ko":"티어스 오브 워리어","jp":"ティアーズオブウォーリア","icon":"WP_DualWeapon_G4_005.png","top":["8,0.7271%,10-1","9,0.4269%,10-2"]},{"id":100230005,"ko":"데스 로드 듀얼 소드","jp":"デスロードデュアルソード","icon":"WP_DualWeapon_G3_005.png","top":["0,1.1640%,10-3","7,1.1640%,10-3"]},{"id":200230002,"ko":"블러드 각반","jp":"ブラッドゲートル","icon":"AR_Pants_G3_002.png","top":["7,3.2641%,10-4","0,0.8127%,10-1","5,0.8127%,10-1"]},{"id":100230002,"ko":"다크 레기온","jp":"ダークリージャンデュアルソード","icon":"WP_DualWeapon_G3_001.png","top":["8,1.8676%,10-5","0,0.3880%,10-2","7,0.3880%,10-2"]},{"id":100240007,"ko":"미스터리 듀얼 소드","jp":"ミステリーデュアルソード","icon":"WP_DualWeapon_G4_007.png","top":["8,0.7271%,10-1","9,0.4269%,10-2"]},{"id":200230003,"ko":"크리스탈 각반","jp":"クリスタルゲートル","icon":"AR_Pants_G3_001.png","top":["7,3.2641%,10-4","0,0.8127%,10-1","5,0.8127%,10-1"]},{"id":100230004,"ko":"마르딜의 분노","jp":"マルディルの怒り","icon":"WP_DualWeapon_G3_004.png","top":["8,1.8676%,10-5","0,0.3880%,10-2","7,0.3880%,10-2"]},{"id":100340005,"ko":"블러디오키드","jp":"ブラッディオーキッド","icon":"WP_Dagger_G4_005.png","top":["8,0.7271%,10-1","9,0.4269%,10-2"]},{"id":100330005,"ko":"플레임 브레이커","jp":"フレイムブレイカー","icon":"WP_Dagger_G3_005.png","top":["0,1.1640%,10-3","7,1.1640%,10-3"]},{"id":200330003,"ko":"다크 크리스탈 글로브","jp":"ダーククリスタルグローブ","icon":"AR_Gloves_G3_002.png","top":["7,3.2641%,10-4","0,0.8127%,10-1","5,0.8127%,10-1"]},{"id":100330003,"ko":"크루마의 뿔","jp":"クルマの角","icon":"WP_Dagger_G3_003.png","top":["8,1.8676%,10-5","0,0.3880%,10-2","7,0.3880%,10-2"]},{"id":100340008,"ko":"마나의 단검","jp":"マナダガー","icon":"WP_Dagger_G4_008.png","top":["8,0.7271%,10-1","9,0.4269%,10-2"]},{"id":200330004,"ko":"마제스틱 장갑","jp":"マジェスティックグローブ","icon":"AR_Gloves_G3_001.png","top":["7,3.2641%,10-4","0,0.8127%,10-1","5,0.8127%,10-1"]},{"id":100330004,"ko":"소울세퍼레이터","jp":"ソウルセパレーター","icon":"WP_Dagger_G3_004.png","top":["8,1.8676%,10-5","0,0.3880%,10-2","7,0.3880%,10-2"]},{"id":100440006,"ko":"문라이트 보우","jp":"ムーンライト·ボウ","icon":"WP_Bow_G4_006.png","top":["8,0.7271%,10-1","9,0.4269%,10-2"]},{"id":100430005,"ko":"플라즈마 보우","jp":"プラズマボウ","icon":"WP_Bow_G3_005.png","top":["0,1.1640%,10-3","7,1.1640%,10-3"]},{"id":200430003,"ko":"다크 크리스탈 부츠","jp":"ダーククリスタルブーツ","icon":"AR_Boots_G3_002.png","top":["7,3.2641%,10-4","0,0.8127%,10-1","5,0.8127%,10-1"]},{"id":100430001,"ko":"카르니움 보우","jp":"カルニウムボウ","icon":"WP_Bow_G3_002.png","top":["8,1.8676%,10-5","0,0.3880%,10-2","7,0.3880%,10-2"]},{"id":100440008,"ko":"악마의 활","jp":"デーモンボウ","icon":"WP_Bow_G4_008.png","top":["8,0.7271%,10-1","9,0.4269%,10-2"]},{"id":200430004,"ko":"마제스틱 부츠","jp":"マジェスティックブーツ","icon":"AR_Boots_G3_001.png","top":["7,3.2641%,10-4","0,0.8127%,10-1","5,0.8127%,10-1"]},{"id":100430004,"ko":"영혼의 활","jp":"ソウルボウ","icon":"WP_Bow_G3_004.png","top":["8,1.8676%,10-5","0,0.3880%,10-2","7,0.3880%,10-2"]},{"id":100540005,"ko":"망자의 지팡이","jp":"アンデッドスタッフ","icon":"WP_Staff_G4_005.png","top":["8,0.7271%,10-1","9,0.4269%,10-2"]},{"id":100530006,"ko":"블러디 네뷸라이트","jp":"ブラッディ·ネビュライト","icon":"WP_Staff_G3_006.png","top":["0,1.1640%,10-3","7,1.1640%,10-3"]},{"id":200530002,"ko":"다크 크리스탈 헬멧","jp":"ダーククリスタルヘルメット","icon":"AR_Helmet_G3_002.png","top":["7,3.2641%,10-4","0,0.8127%,10-1","5,0.8127%,10-1"]},{"id":100530002,"ko":"세계수의 가지","jp":"世界樹の枝","icon":"WP_Staff_G3_001.png","top":["8,1.8676%,10-5","0,0.3880%,10-2","7,0.3880%,10-2"]},{"id":100540008,"ko":"생명의 가지","jp":"命の枝","icon":"WP_Staff_G4_008.png","top":["8,0.7271%,10-1","9,0.4269%,10-2"]},{"id":200530003,"ko":"마제스틱 서클릿","jp":"マジェスティックサークレット","icon":"AR_Helmet_G3_001.png","top":["7,3.2641%,10-4","0,0.8127%,10-1","5,0.8127%,10-1"]},{"id":100530004,"ko":"스타카토 퀸의 지팡이","jp":"スタッカートクイーンスタッフ","icon":"WP_Staff_G3_004.png","top":["8,1.8676%,10-5","0,0.3880%,10-2","7,0.3880%,10-2"]},{"id":100640006,"ko":"너바나","jp":"ニルヴァーナ","icon":"WP_Orb_G4_006.png","top":["8,0.7271%,10-1","9,0.4269%,10-2"]},{"id":100630001,"ko":"드래곤 플레임 헤드","jp":"ドラゴンオーブ","icon":"WP_Orb_G3_002.png","top":["0,1.1640%,10-3","7,1.1640%,10-3"]},{"id":200630002,"ko":"자켄의 망토","jp":"ザケンクローク","icon":"AR_Cape_G3_004.png","top":["7,3.2641%,10-4","0,0.8127%,10-1","5,0.8127%,10-1"]},{"id":100530005,"ko":"정령의 지팡이","jp":"精霊のスタッフ","icon":"WP_Staff_G3_005.png","top":["8,1.8676%,10-5","0,0.3880%,10-2","7,0.3880%,10-2"]},{"id":100640008,"ko":"페어리 퀸","jp":"フェアリークイーン","icon":"WP_Orb_G4_008.png","top":["8,0.7271%,10-1","9,0.4269%,10-2"]},{"id":200630003,"ko":"프레야의 망토","jp":"フレヤクローク","icon":"AR_Cape_G3_003.png","top":["7,3.2641%,10-4","0,0.8127%,10-1","5,0.8127%,10-1"]},{"id":100630004,"ko":"영혼의 눈","jp":"ソウルズアイ","icon":"WP_Orb_G3_004.png","top":["8,1.8676%,10-5","0,0.3880%,10-2","7,0.3880%,10-2"]},{"id":100740006,"ko":"사이드","jp":"サイス","icon":"WP_Spear_G4_006.png","top":["8,0.7271%,10-1","9,0.4269%,10-2"]},{"id":100630005,"ko":"엘리시온","jp":"エリージャン","icon":"WP_Orb_G3_005.png","top":["0,1.1640%,10-3","7,1.1640%,10-3"]},{"id":200830005,"ko":"업화의 시길","jp":"業火のシギル","icon":"AR_Sigil_G3_005.png","top":["1,3.5608%,10-4","0,0.3880%,10-2"]},{"id":100730001,"ko":"탈룸 글레이브","jp":"タラムグレイブ","icon":"WP_Spear_G3_001.png","top":["8,1.8676%,10-5","0,0.3880%,10-2","7,0.3880%,10-2"]},{"id":100740008,"ko":"배틀 스피어","jp":"バトルスピアー","icon":"WP_Spear_G4_008.png","top":["8,0.7271%,10-1","9,0.4269%,10-2"]},{"id":300130003,"ko":"바이움의 목걸이","jp":"バイウムネックレス","icon":"ACC_Necklace_G3_003.png","top":["3,3.5608%,10-4","1,0.5045%,10-2"]},{"id":100730004,"ko":"핼버드","jp":"ハルバード","icon":"WP_Spear_G3_004.png","top":["8,1.8676%,10-5","0,0.3880%,10-2","7,0.3880%,10-2"]},{"id":100940006,"ko":"인페르노 마스터","jp":"インフェルノマスター","icon":"WP_GreatSword_G4_006.png","top":["8,0.7271%,10-1","9,0.4269%,10-2"]},{"id":100730005,"ko":"아스칼론","jp":"アスカロン","icon":"WP_Spear_G3_005.png","top":["0,1.1640%,10-3","7,1.1640%,10-3"]},{"id":300130005,"ko":"오르펜의 목걸이","jp":"オルフェンネックレス","icon":"ACC_Necklace_G3_001.png","top":["3,3.5608%,10-4","1,0.5045%,10-2"]},{"id":100930001,"ko":"카오스 브레이커","jp":"カオスブレイカー","icon":"WP_GreatSword_G3_001.png","top":["8,1.8676%,10-5","0,0.3880%,10-2","7,0.3880%,10-2"]},{"id":100940008,"ko":"사령의 대검","jp":"エビルスピリットグレートソード","icon":"WP_GreatSword_G4_008.png","top":["8,0.7271%,10-1","9,0.4269%,10-2"]},{"id":300130006,"ko":"불사의 목걸이","jp":"不死のネックレス","icon":"ACC_Necklace_G3_006.png","top":["3,3.5608%,10-4","1,0.5045%,10-2"]},{"id":100930004,"ko":"헤븐즈 윙블레이드","jp":"ヘブンズウイングブレード","icon":"WP_GreatSword_G3_004.png","top":["8,1.8676%,10-5","0,0.3880%,10-2","7,0.3880%,10-2"]},{"id":100840004,"ko":"피스메이커","jp":"ピースメーカー","icon":"WP_Crossbow_G4_004.png","top":["8,0.7271%,10-1","9,0.4269%,10-2"]},{"id":101130004,"ko":"레바테인","jp":"レーヴァテイン","icon":"WP_Rapier_G3_004.png","top":["0,1.1640%,10-3","7,1.1640%,10-3"]},{"id":300130010,"ko":"광휘의 목걸이","jp":"光輝のネックレス","icon":"ACC_Necklace_G3_010.png","top":["1,3.2641%,10-4"]},{"id":100930005,"ko":"드래곤 슬레이어","jp":"ドラゴンスレイヤー","icon":"WP_GreatSword_G3_005.png","top":["8,1.8676%,10-5","0,0.3880%,10-2","7,0.3880%,10-2"]},{"id":100840006,"ko":"앤틱 크로스보우","jp":"アンティーククロスボウ","icon":"WP_Crossbow_G4_006.png","top":["8,0.7271%,10-1","9,0.4269%,10-2"]},{"id":300330007,"ko":"잊혀진 영웅의 반지","jp":"忘れられた英雄のリング","icon":"ACC_Ring_G3_007.png","top":["3,3.5608%,10-4","1,0.5045%,10-2"]},{"id":100830001,"ko":"쏜 크로스보우","jp":"ソーンクロスボウ","icon":"WP_Crossbow_G3_001.png","top":["8,1.8676%,10-5","0,0.3880%,10-2","7,0.3880%,10-2"]},{"id":101040006,"ko":"디스멘틀러","jp":"ディスメントラー","icon":"WP_ChainSword_G4_006.png","top":["8,0.7271%,10-1","9,0.4269%,10-2"]},{"id":101230004,"ko":"제피로스","jp":"","icon":"WP_MagicCannon_G3_004.png","top":["0,1.1640%,10-3","7,1.1640%,10-3"]},{"id":300330011,"ko":"광휘의 반지","jp":"光輝のリング","icon":"ACC_Ring_G3_011.png","top":["1,3.2641%,10-4"]},{"id":100830004,"ko":"소울 슈터","jp":"ソウルシューター","icon":"WP_Crossbow_G3_004.png","top":["8,1.8676%,10-5","0,0.3880%,10-2","7,0.3880%,10-2"]},{"id":101040008,"ko":"라이트닝 체인소드","jp":"ライトニング·チェーンソード","icon":"WP_ChainSword_G4_008.png","top":["8,0.7271%,10-1","9,0.4269%,10-2"]},{"id":300330012,"ko":"불사의 반지","jp":"","icon":"ACC_Ring_G3_012.png","top":["1,3.2641%,10-4"]},{"id":100830005,"ko":"버스트 어벤져","jp":"バーストアベンジャー","icon":"WP_Crossbow_G3_005.png","top":["8,1.8676%,10-5","0,0.3880%,10-2","7,0.3880%,10-2"]},{"id":101140008,"ko":"콜리슈마르드","jp":"コリシュマルド","icon":"WP_Rapier_G4_008.png","top":["8,0.7271%,10-1","9,0.4269%,10-2"]},{"id":200230004,"ko":"빛의 각반","jp":"ライトゲートル","icon":"AR_Pants_G3_004.png","top":["0,1.1640%,10-3","5,1.1640%,10-3"]},{"id":300430003,"ko":"드래곤 벨트","jp":"ドラゴンベルト","icon":"ACC_Belt_G3_003.png","top":["3,3.5608%,10-4","1,0.5045%,10-2"]},{"id":101030001,"ko":"드래곤 헌터","jp":"ドラゴンハンター","icon":"WP_ChainSword_G3_001.png","top":["8,1.8676%,10-5","0,0.3880%,10-2","7,0.3880%,10-2"]},{"id":101140006,"ko":"그리드 레이피어","jp":"グリードレイピア","icon":"WP_Rapier_G4_006.png","top":["8,0.7271%,10-1","9,0.4269%,10-2"]},{"id":100110001,"ko":"펜던트 강화 주문서 10~15개","jp":"","icon":"WP_Sword_G1_001.png","top":["0,19.8813%,10-4"]},{"id":101030002,"ko":"그람","jp":"グラム","icon":"WP_ChainSword_G3_002.png","top":["8,1.8676%,10-5","0,0.3880%,10-2","7,0.3880%,10-2"]},{"id":101240008,"ko":"스타 버스터","jp":"","icon":"WP_MagicCannon_G4_002.png","top":["8,0.7271%,10-1","9,0.4269%,10-2"]},{"id":200230008,"ko":"인내의 각반","jp":"忍耐のゲートル","icon":"AR_Pants_G3_008.png","top":["0,1.1640%,10-3","5,1.1640%,10-3"]},{"id":701040009,"ko":"그레시아 커맨더의 마력석","jp":"グレシアコマンダーの魔力石","icon":"Item_Misc_Gracia_Collection_A.png","top":["5,3.2641%,10-4"]},{"id":101030004,"ko":"페인 오브 가드네스","jp":"ペイン·オブ·ガードネス","icon":"WP_ChainSword_G3_004.png","top":["8,1.8676%,10-5","0,0.3880%,10-2","7,0.3880%,10-2"]},{"id":101240006,"ko":"데스브링거","jp":"","icon":"WP_MagicCannon_G4_001.png","top":["8,0.7271%,10-1","9,0.4269%,10-2"]},{"id":701040010,"ko":"그레시아 슈페리어의 마력석","jp":"グレシアスーペリアの魔力石","icon":"Item_Misc_Gracia_Collection_B.png","top":["5,3.2641%,10-4"]},{"id":101130005,"ko":"오트클레르","jp":"オートクレール","icon":"WP_Rapier_G3_005.png","top":["8,1.8676%,10-5","0,0.3880%,10-2","7,0.3880%,10-2"]},{"id":200330001,"ko":"축복의 장갑","jp":"ブレッシンググローブ","icon":"AR_Gloves_G3_004.png","top":["0,1.1640%,10-3","5,1.1640%,10-3"]},{"id":701040011,"ko":"그레시아 노비스의 마력석","jp":"グレシアノービスの魔力石","icon":"Item_Misc_Gracia_Collection_C.png","top":["5,3.2641%,10-4"]},{"id":101130001,"ko":"바리사다","jp":"バリサダ","icon":"WP_Rapier_G3_001.png","top":["8,1.8676%,10-5","0,0.3880%,10-2","7,0.3880%,10-2"]},{"id":101230005,"ko":"디바인 블래스터","jp":"","icon":"WP_MagicCannon_G3_001.png","top":["8,1.8676%,10-5","0,0.3880%,10-2","7,0.3880%,10-2"]},{"id":200330005,"ko":"야른그레이프르","jp":"ヤールングレイプル","icon":"AR_Gloves_G3_005.png","top":["0,1.1640%,10-3","5,1.1640%,10-3"]},{"id":101230001,"ko":"스코필드","jp":"","icon":"WP_MagicCannon_G3_005.png","top":["8,1.8676%,10-5","0,0.3880%,10-2","7,0.3880%,10-2"]},{"id":200130003,"ko":"악몽의 갑옷","jp":"ナイトメアアーマー","icon":"AR_Torso_G3_003.png","top":["6,2.2071%,10-5"]},{"id":200140001,"ko":"푸른 늑대의 흉갑","jp":"ウルーウルヴズブレストプレート","icon":"AR_Torso_G4_004.png","top":["7,0.5560%,10-1"]},{"id":200330013,"ko":"스턴 건틀렛","jp":"スタン·ガントレット","icon":"AR_Gloves_G3_013.png","top":["0,1.1640%,10-3","5,1.1640%,10-3"]},{"id":200230001,"ko":"실렌의 숨결","jp":"シーレンの息吹","icon":"AR_Pants_G3_003.png","top":["6,2.2071%,10-5"]},{"id":200230005,"ko":"빙결의 각반","jp":"アイスゲートル","icon":"AR_Pants_G3_005.png","top":["6,2.2071%,10-5"]},{"id":200330014,"ko":"인내의 장갑","jp":"忍耐のグローブ","icon":"AR_Gloves_G3_014.png","top":["0,1.1640%,10-3","5,1.1640%,10-3"]},{"id":200330002,"ko":"악몽의 건틀렛","jp":"ナイトメアガントレット","icon":"AR_Gloves_G3_003.png","top":["6,2.2071%,10-5"]},{"id":200430002,"ko":"악몽의 부츠","jp":"ナイトメアブーツ","icon":"AR_Boots_G3_003.png","top":["6,2.2071%,10-5"]},{"id":200430011,"ko":"영생의 부츠","jp":"エタニティブーツ","icon":"AR_Boots_G3_011.png","top":["0,1.1640%,10-3","5,1.1640%,10-3"]},{"id":200530001,"ko":"악몽의 투구","jp":"ナイトメアヘルム","icon":"AR_Helmet_G3_003.png","top":["6,2.2071%,10-5"]},{"id":200240001,"ko":"푸른 늑대의 각반","jp":"ブルーウルヴズゲートル","icon":"AR_Pants_G4_003.png","top":["7,0.5560%,10-1"]},{"id":200630005,"ko":"침묵의 망토","jp":"サイレントクローク","icon":"AR_Cape_G3_001.png","top":["6,2.2071%,10-5"]},{"id":200240005,"ko":"심연의 각반","jp":"アビスゲートル","icon":"AR_Pants_G4_005.png","top":["7,0.5560%,10-1"]},{"id":200430012,"ko":"사신의 부츠","jp":"死神のブーツ","icon":"AR_Boots_G3_012.png","top":["0,1.1640%,10-3","5,1.1640%,10-3"]},{"id":200830002,"ko":"스나이퍼 시길","jp":"スナイパー·シギル","icon":"AR_Sigil_G3_002.png","top":["3,1.6978%,10-5","0,0.8127%,10-1"]},{"id":200830003,"ko":"패러디아 시길","jp":"パラディアシギル","icon":"AR_Sigil_G3_001.png","top":["3,1.6978%,10-5","0,0.8127%,10-1"]},{"id":200530004,"ko":"메두사의 투구","jp":"メデューサヘルム","icon":"AR_Helmet_G3_004.png","top":["0,1.1640%,10-3","5,1.1640%,10-3"]},{"id":200830006,"ko":"셀리호든의 뿔","jp":"シェリーホドンの角","icon":"AR_Sigil_G3_006.png","top":["1,2.2071%,10-5","0,1.1640%,10-3"]},{"id":200830007,"ko":"망각의 크리스탈","jp":"忘却のクリスタル","icon":"AR_Sigil_G3_007.png","top":["1,2.2071%,10-5","0,1.1640%,10-3"]},{"id":200530010,"ko":"힐데그림","jp":"ヒルデグリム","icon":"AR_Helmet_G3_010.png","top":["0,1.1640%,10-3","5,1.1640%,10-3"]},{"id":200840001,"ko":"블러드 크리스탈","jp":"ブラッド·クリスタル","icon":"AR_Sigil_G4_002.png","top":["5,1.6978%,10-5","3,0.5560%,10-1"]},{"id":200340001,"ko":"푸른 늑대의 장갑","jp":"ブルーウルヴズグローブ","icon":"AR_Gloves_G4_006.png","top":["7,0.5560%,10-1"]},{"id":200840004,"ko":"엘다라크","jp":"エルダラク","icon":"AR_Sigil_G4_004.png","top":["5,1.6978%,10-5","3,0.5560%,10-1"]},{"id":200340008,"ko":"아벨리우스의 건틀렛","jp":"アベリウスのガントレット","icon":"AR_Gloves_G4_008.png","top":["7,0.5560%,10-1"]},{"id":200630008,"ko":"셀리호든의 날개","jp":"シェリーホドンの翼","icon":"AR_Cape_G3_008.png","top":["0,1.1640%,10-3","5,1.1640%,10-3"]},{"id":200840005,"ko":"페이탈 시길","jp":"フェイタルシギル","icon":"AR_Sigil_G4_005.png","top":["5,1.6978%,10-5","3,0.5560%,10-1"]},{"id":200340010,"ko":"신궁의 글로브","jp":"エースグローブ","icon":"AR_Gloves_G4_010.png","top":["7,0.5560%,10-1"]},{"id":100110001,"ko":"영원의 돌 10~15개","jp":"","icon":"WP_Sword_G1_001.png","top":["0,21.2224%,10-5"]},{"id":200640007,"ko":"헤르문쿠스의 망토","jp":"ヘルムンクスクローク","icon":"AR_Cape_G4_007.png","top":["9,1.0582%,10-3","8,0.5560%,10-1"]},{"id":300130001,"ko":"릴리스의 영혼 목걸이","jp":"リリスのソウルネックレス","icon":"ACC_Necklace_G3_005.png","top":["0,1.1640%,10-3"]},{"id":200440006,"ko":"푸른 늑대의 부츠","jp":"ブルーウルヴズブーツ","icon":"AR_Boots_G4_006.png","top":["7,0.5560%,10-1"]},{"id":300130002,"ko":"아나킴의 영혼 목걸이","jp":"アナキムのソウルネックレス","icon":"ACC_Necklace_G3_004.png","top":["0,1.1640%,10-3"]},{"id":300130004,"ko":"자켄의 목걸이","jp":"ザケンネックレス","icon":"ACC_Necklace_G3_002.png","top":["0,1.1640%,10-3"]},{"id":300130007,"ko":"마제스틱 네크리스","jp":"マジェスティックネックレス","icon":"ACC_Necklace_G3_007.png","top":["1,1.1640%,10-3","0,0.3880%,10-2"]},{"id":300130008,"ko":"아펠라의 목걸이","jp":"アペラのネックレス","icon":"ACC_Necklace_G4_007.png","top":["1,1.1640%,10-3","0,0.3880%,10-2"]},{"id":300130009,"ko":"은총의 목걸이","jp":"グレースネックレス","icon":"ACC_Necklace_G3_009.png","top":["1,1.1640%,10-3","0,0.3880%,10-2"]},{"id":200540003,"ko":"푸른 늑대의 헬멧","jp":"ブルーウルヴズヘルム","icon":"AR_Helmet_G4_003.png","top":["7,0.5560%,10-1"]},{"id":300330001,"ko":"릴리스의 반지","jp":"リリスリング","icon":"ACC_Ring_G3_006.png","top":["1,1.1640%,10-3","0,0.3880%,10-2"]},{"id":200540005,"ko":"라키시스의 모자","jp":"ラキシスフード","icon":"AR_Helmet_G4_005.png","top":["7,0.5560%,10-1"]},{"id":300330002,"ko":"아나킴의 반지","jp":"アナキムリング","icon":"ACC_Ring_G3_005.png","top":["0,1.1640%,10-3"]},{"id":300330003,"ko":"바이움의 반지","jp":"バイウムリング","icon":"ACC_Ring_G3_004.png","top":["1,1.1640%,10-3","0,0.3880%,10-2"]},{"id":300330004,"ko":"베레스의 반지","jp":"ベレスリング","icon":"ACC_Ring_G3_003.png","top":["1,1.1640%,10-3","0,0.3880%,10-2"]},{"id":300330005,"ko":"코어의 반지","jp":"コアリング","icon":"ACC_Ring_G3_002.png","top":["1,1.1640%,10-3","0,0.3880%,10-2"]},{"id":300330006,"ko":"여왕개미의 심장","jp":"クイーンアントハート","icon":"ACC_Ring_G3_001.png","top":["1,1.1640%,10-3","0,0.3880%,10-2"]},{"id":200640002,"ko":"샐러맨더의 망토","jp":"サラマンダークローク","icon":"AR_Cape_G4_003.png","top":["7,0.5560%,10-1"]},{"id":300330009,"ko":"마제스틱 링","jp":"マジェスティックリング","icon":"ACC_Ring_G3_009.png","top":["1,1.1640%,10-3","0,0.3880%,10-2"]},{"id":200640005,"ko":"메두사의 망토","jp":"メデューサクローク","icon":"AR_Cape_G4_005.png","top":["7,0.5560%,10-1"]},{"id":300330010,"ko":"데스 로드의 반지","jp":"デスロードリング","icon":"ACC_Ring_G3_010.png","top":["0,1.1640%,10-3"]},{"id":200640006,"ko":"크론비스트의 망토","jp":"クローンビーストクローク","icon":"AR_Cape_G4_006.png","top":["7,0.5560%,10-1"]},{"id":300430001,"ko":"티아트의 벨트","jp":"ティアトのベルト","icon":"ACC_Belt_G3_002.png","top":["1,1.1640%,10-3","0,0.3880%,10-2"]},{"id":300430004,"ko":"에라토네의 벨트","jp":"エラトネのベルト","icon":"ACC_Belt_G3_004.png","top":["1,1.1640%,10-3","0,0.3880%,10-2"]},{"id":200640008,"ko":"군주의 망토","jp":"血盟主のクローク","icon":"AR_Cape_G4_008.png","top":["7,0.5560%,10-1"]},{"id":300430005,"ko":"옥타비스의 벨트","jp":"オクタビスのベルト","icon":"ACC_Belt_G3_005.png","top":["1,1.1640%,10-3","0,0.3880%,10-2"]},{"id":200740004,"ko":"용사의 티셔츠","jp":"勇者のシャツ","icon":"AR_Tshirt_G4_004.png","top":["7,0.5560%,10-1"]},{"id":500313007,"ko":"전투 기술서 (홀리 스트라이크)","jp":"戦闘技術書(ホーリーストライク)","icon":"Item_Usable_SkillBook_Sword_04.png","top":["0,1.1640%,10-3"]},{"id":200750001,"ko":"완력의 무명 셔츠","jp":"腕力の木綿シャツ","icon":"AR_Tshirt_G5_003.png","top":["9,0.4705%,10-1"]},{"id":500313008,"ko":"전투 기술서 (스트라이크 포스)","jp":"戦闘技術書(ストライクフォース)","icon":"Item_Usable_SkillBook_Sword_04.png","top":["0,1.1640%,10-3"]},{"id":200750002,"ko":"민첩의 무명 셔츠","jp":"敏捷の木綿シャツ","icon":"AR_Tshirt_G5_002.png","top":["9,0.4705%,10-1"]},{"id":500323007,"ko":"이도류 비전서 (듀얼 패링)","jp":"二刀流秘伝書(デュアルパリィ)","icon":"Item_Usable_SkillBook_Dual_04.png","top":["0,1.1640%,10-3"]},{"id":200750003,"ko":"지식의 무명 셔츠","jp":"知識の木綿シャツ","icon":"AR_Tshirt_G5_001.png","top":["9,0.4705%,10-1"]},{"id":500323008,"ko":"이도류 비전서 (소닉 마스터리)","jp":"二刀流秘伝書(ソニックマスタリー)","icon":"Item_Usable_SkillBook_Dual_04.png","top":["0,1.1640%,10-3"]},{"id":200750004,"ko":"집중의 셔츠","jp":"集中のシャツ","icon":"AR_Tshirt_G5_004.png","top":["9,0.4705%,10-1"]},{"id":500333007,"ko":"암살 비급 (리셋 무브먼트)","jp":"暗殺秘本(リセットムーブメント)","icon":"Item_Usable_SkillBook_Dagger_04.png","top":["0,1.1640%,10-3"]},{"id":200750005,"ko":"자경대원 셔츠","jp":"自警団員のシャツ","icon":"AR_Tshirt_G5_005.png","top":["9,0.4705%,10-1"]},{"id":500333008,"ko":"암살 비급 (포이즌 테러)","jp":"暗殺秘本(ポイズンテロ)","icon":"Item_Usable_SkillBook_Dagger_04.png","top":["0,1.1640%,10-3"]},{"id":500343007,"ko":"궁술 교본 (임팩트 샷)","jp":"弓術教本(インパクトショット)","icon":"Item_Usable_SkillBook_Bow_04.png","top":["0,1.1640%,10-3"]},{"id":500343008,"ko":"궁술 교본 (퀵 드로우)","jp":"弓術教本(クイックドロー)","icon":"Item_Usable_SkillBook_Bow_04.png","top":["0,1.1640%,10-3"]},{"id":500353008,"ko":"마도서 (프로즌 크리스탈)","jp":"魔導書(フローズンクリスタル)","icon":"Item_Usable_SkillBook_Staff_04.png","top":["0,1.1640%,10-3"]},{"id":100110001,"ko":"마도서 (데블스 웨이)","jp":"","icon":"WP_Sword_G1_001.png","top":["0,1.1640%,10-3"]},{"id":500363010,"ko":"사제의 기록 (디바인 엑스큐션)","jp":"司祭録(ディヴァインエクスキューション)","icon":"Item_Usable_SkillBook_Orb_04.png","top":["0,1.1640%,10-3"]},{"id":200850008,"ko":"신수의 꽃잎","jp":"神樹の花びら","icon":"AR_Sigil_G5_008.png","top":["5,0.4705%,10-1"]},{"id":500363011,"ko":"사제의 기록 (라스트 힐)","jp":"司祭録(ラストヒール)","icon":"Item_Usable_SkillBook_Orb_04.png","top":["0,1.1640%,10-3"]},{"id":300140005,"ko":"각성의 목걸이","jp":"覚醒のネックレス","icon":"ACC_Necklace_G4_005.png","top":["5,0.4705%,10-1"]},{"id":500373001,"ko":"창술서 (자이언트 스톰프)","jp":"槍術書(ジャイアントストンプ)","icon":"Item_Usable_SkillBook_Spear_04.png","top":["0,1.1640%,10-3"]},{"id":300140006,"ko":"기원의 목걸이","jp":"祈りのネックレス","icon":"ACC_Necklace_G4_006.png","top":["5,0.6843%,10-1"]},{"id":500373008,"ko":"창술서 (피스 오브 마인드)","jp":"槍術書(ピース·オブ·マインド)","icon":"Item_Usable_SkillBook_Spear_04.png","top":["0,1.1640%,10-3"]},{"id":300240001,"ko":"인페르노 이어링","jp":"インフェルノイアリング","icon":"ACC_Earring_G4_001.png","top":["5,0.6843%,10-1"]},{"id":500383002,"ko":"대검 전술서 (리플렉트 스턴)","jp":"両手剣戦術書(リフレクトスタン)","icon":"Item_Usable_SkillBook_GreatSword_04.png","top":["0,1.1640%,10-3"]},{"id":300240002,"ko":"나센의 귀걸이","jp":"ナッセンのイヤリング","icon":"ACC_Earring_G4_002.png","top":["5,0.6843%,10-1"]},{"id":500383003,"ko":"대검 전술서 (헬 파이어)","jp":"両手剣戦術書(ヘルファイア)","icon":"Item_Usable_SkillBook_GreatSword_04.png","top":["0,1.1640%,10-3"]},{"id":300240003,"ko":"마염의 귀걸이","jp":"マジックフレイムイヤリング","icon":"ACC_Earring_G4_003.png","top":["5,0.6843%,10-1"]},{"id":200130001,"ko":"아펠라의 갑주","jp":"アペラアーマー","icon":"AR_Torso_G3_005.png","top":["0,0.3880%,10-2","5,0.3880%,10-2"]},{"id":500393006,"ko":"석궁 훈련서 (체인 볼트)","jp":"クロスボウ訓練書(チェーンボルト)","icon":"Item_Usable_SkillBook_CrossBow_04.png","top":["0,1.1640%,10-3"]},{"id":300330008,"ko":"열정의 반지","jp":"パッションリング","icon":"ACC_Ring_G3_008.png","top":["0,0.8127%,10-1","1,0.6416%,10-1","3,0.4269%,10-2"]},{"id":500393008,"ko":"석궁 훈련서 (블랙아웃 볼트 샷)","jp":"クロスボウ訓練書(ブラックアウトボルトショット)","icon":"Item_Usable_SkillBook_CrossBow_04.png","top":["0,1.1640%,10-3"]},{"id":200130002,"ko":"앱솔루트 튜닉","jp":"アブソリュートチューニック","icon":"AR_Torso_G3_004.png","top":["0,0.3880%,10-2","5,0.3880%,10-2"]},{"id":503293004,"ko":"마검 비술서 (바인딩)","jp":"魔剣秘術書(バインディング)","icon":"Item_Usable_SkillBook_ChainSword_04.png","top":["0,1.1640%,10-3"]},{"id":300340003,"ko":"물의 수호 반지","jp":"水のプロテクションリング","icon":"ACC_Ring_G4_006.png","top":["5,0.4705%,10-1"]},{"id":503293008,"ko":"마검 비술서 (블러디 소드)","jp":"魔剣秘術書(ブラッディソード)","icon":"Item_Usable_SkillBook_ChainSword_04.png","top":["0,1.1640%,10-3"]},{"id":300340004,"ko":"땅의 수호 반지","jp":"地のプロテクションリング","icon":"ACC_Ring_G4_005.png","top":["5,0.4705%,10-1"]},{"id":200130006,"ko":"사반의 로브","jp":"サヴァンローブ","icon":"AR_Torso_G3_006.png","top":["0,0.3880%,10-2","5,0.3880%,10-2"]},{"id":503203002,"ko":"세검 지도서 (슈팅 스타 Ⅰ)","jp":"細身剣指導書(シューティングスターⅠ)","icon":"Item_Usable_SkillBook_Rapier_04.png","top":["0,1.1640%,10-3"]},{"id":300340005,"ko":"바람의 수호 반지","jp":"風のプロテクションリング","icon":"ACC_Ring_G4_004.png","top":["5,0.4705%,10-1"]},{"id":503203006,"ko":"세검 지도서 (소드 블라썸)","jp":"細身剣指導書(ソードブロッサム)","icon":"Item_Usable_SkillBook_Rapier_04.png","top":["0,1.1640%,10-3"]},{"id":300340006,"ko":"불의 수호 반지","jp":"火のプロテクションリング","icon":"ACC_Ring_G4_003.png","top":["5,0.4705%,10-1"]},{"id":200130007,"ko":"폴리네의 흉갑","jp":"ポリーネのブレストプレート","icon":"AR_Torso_G3_007.png","top":["0,0.3880%,10-2","7,0.3880%,10-2"]},{"id":503213006,"ko":"마법 공학서 (슬립)","jp":"","icon":"Item_Usable_SkillBook_MagicCannon_04.png","top":["0,1.1640%,10-3"]},{"id":300340007,"ko":"암흑의 수호 반지","jp":"闇のプロテクションリング","icon":"ACC_Ring_G4_002.png","top":["5,0.4705%,10-1"]},{"id":503213008,"ko":"마법 공학서 (캐논 익스펜션)","jp":"","icon":"Item_Usable_SkillBook_MagicCannon_04.png","top":["0,1.1640%,10-3"]},{"id":300340008,"ko":"신성의 수호 반지","jp":"聖のプロテクションリング","icon":"ACC_Ring_G4_001.png","top":["5,0.4705%,10-1"]},{"id":200130008,"ko":"네비트의 갑옷","jp":"ネビトのアーマー","icon":"AR_Torso_G3_008.png","top":["0,0.3880%,10-2","7,0.3880%,10-2"]},{"id":300430002,"ko":"에키무스의 벨트","jp":"エキムスのベルト","icon":"ACC_Belt_G3_001.png","top":["0,0.8127%,10-1","1,0.6416%,10-1","3,0.4269%,10-2"]},{"id":200130009,"ko":"테르시의 로브","jp":"テルシのローブ","icon":"AR_Torso_G3_009.png","top":["0,0.3880%,10-2","7,0.3880%,10-2"]},{"id":300440001,"ko":"축복의 벨트","jp":"ブレッシングベルト","icon":"ACC_Belt_G4_002.png","top":["5,0.4705%,10-1"]},{"id":300440002,"ko":"켈베로스 벨트","jp":"ケルベロスベルト","icon":"ACC_Belt_G4_001.png","top":["5,0.4705%,10-1"]},{"id":200130010,"ko":"잊혀진 영웅의 흉갑","jp":"忘れられた英雄のブレストプレート","icon":"AR_Torso_G3_010.png","top":["0,0.3880%,10-2","7,0.3880%,10-2"]},{"id":300540001,"ko":"축복의 팔찌","jp":"ブレッシングブレスレット","icon":"ACC_Bracelet_G4_003.png","top":["5,0.4705%,10-1"]},{"id":300540002,"ko":"은총의 팔찌","jp":"グレースブレスレット","icon":"ACC_Bracelet_G4_002.png","top":["5,0.6843%,10-1"]},{"id":200130011,"ko":"악마의 갑주","jp":"デーモンアーマー","icon":"AR_Torso_G3_011.png","top":["0,0.3880%,10-2","5,0.3880%,10-2"]},{"id":300540003,"ko":"여명의 팔찌","jp":"黎明のブレスレット","icon":"ACC_Bracelet_G4_001.png","top":["5,0.6843%,10-1"]},{"id":300540004,"ko":"아쿠아스톤 팔찌","jp":"アクアストーンブレスレット","icon":"ACC_Bracelet_G4_004.png","top":["5,0.6843%,10-1"]},{"id":200140006,"ko":"심판의 갑옷","jp":"ジャッジメントアーマー","icon":"AR_Torso_G4_006.png","top":["7,0.5821%,10-2"]},{"id":100110001,"ko":"결정체 (각인) 135000~165000개","jp":"","icon":"WP_Sword_G1_001.png","top":["0,8.5115%,10-1"]},{"id":200140007,"ko":"둠 플레이트 아머","jp":"ドゥームプレートアーマー","icon":"AR_Torso_G4_007.png","top":["7,0.5821%,10-2"]},{"id":100110001,"ko":"고급 결정체 (각인) 900~1100개","jp":"","icon":"WP_Sword_G1_001.png","top":["0,8.5115%,10-1"]},{"id":200140008,"ko":"혼돈의 흉갑","jp":"混沌のブレストプレート","icon":"AR_Torso_G4_008.png","top":["7,0.5821%,10-2"]},{"id":100110001,"ko":"영원의 돌 1개","jp":"","icon":"WP_Sword_G1_001.png","top":["0,8.5115%,10-1"]},{"id":200230006,"ko":"잊혀진 영웅의 각반","jp":"忘れられた英雄のゲートル","icon":"AR_Pants_G3_006.png","top":["0,0.3880%,10-2","5,0.3880%,10-2"]},{"id":100110001,"ko":"영원의 돌 2개","jp":"","icon":"WP_Sword_G1_001.png","top":["0,6.3730%,10-1"]},{"id":100110001,"ko":"영원의 돌 3개","jp":"","icon":"WP_Sword_G1_001.png","top":["0,4.2772%,10-1"]},{"id":200230007,"ko":"화염의 각반","jp":"フレイムゲートル","icon":"AR_Pants_G3_007.png","top":["0,0.3880%,10-2","5,0.3880%,10-2"]},{"id":200240006,"ko":"호즈 오브 둠","jp":"ドゥームホース","icon":"AR_Pants_G4_006.png","top":["7,0.5821%,10-2"]},{"id":200240007,"ko":"심판의 각반","jp":"ジャッジメントゲートル","icon":"AR_Pants_G4_007.png","top":["7,0.5821%,10-2"]},{"id":200240008,"ko":"혼돈의 각반","jp":"混沌のゲートル","icon":"AR_Pants_G4_008.png","top":["7,0.5821%,10-2"]},{"id":200240009,"ko":"사념의 호즈","jp":"思念のホース","icon":"AR_Pants_G4_009.png","top":["7,0.5821%,10-2"]},{"id":200330006,"ko":"비전의 수호자","jp":"シークレットガーディアン","icon":"AR_Gloves_G3_006.png","top":["0,0.3880%,10-2","7,0.3880%,10-2"]},{"id":200330007,"ko":"폴리네의 건틀렛","jp":"ポリーネのガントレット","icon":"AR_Gloves_G3_007.png","top":["0,0.3880%,10-2","7,0.3880%,10-2"]},{"id":200330008,"ko":"네비트의 글로브","jp":"ネビトのグローブ","icon":"AR_Gloves_G3_008.png","top":["0,0.3880%,10-2","7,0.3880%,10-2"]},{"id":200330009,"ko":"테르시의 장갑","jp":"テルシのグローブ","icon":"AR_Gloves_G3_009.png","top":["0,0.3880%,10-2","7,0.3880%,10-2"]},{"id":200330010,"ko":"잊혀진 영웅의 글로브","jp":"忘れられた英雄のグローブ","icon":"AR_Gloves_G3_010.png","top":["0,0.3880%,10-2","7,0.3880%,10-2"]},{"id":200330011,"ko":"악마의 건틀렛","jp":"デーモンガントレット","icon":"AR_Gloves_G3_011.png","top":["0,0.3880%,10-2","5,0.3880%,10-2"]},{"id":200340011,"ko":"심판의 글로브","jp":"ジャッジメントグローブ","icon":"AR_Gloves_G4_011.png","top":["7,0.5821%,10-2"]},{"id":200340012,"ko":"둠 플레이트 건틀렛","jp":"ドゥームプレートガントレット","icon":"AR_Gloves_G4_012.png","top":["7,0.5821%,10-2"]},{"id":200340013,"ko":"혼돈의 건틀렛","jp":"混沌のガントレット","icon":"AR_Gloves_G4_013.png","top":["7,0.5821%,10-2"]},{"id":200430001,"ko":"악마의 부츠","jp":"デーモンブーツ","icon":"AR_Boots_G3_004.png","top":["0,0.3880%,10-2","5,0.3880%,10-2"]},{"id":200430005,"ko":"폴리네의 부츠","jp":"ポリーネのブーツ","icon":"AR_Boots_G3_005.png","top":["0,0.3880%,10-2","7,0.3880%,10-2"]},{"id":200430006,"ko":"네비트의 부츠","jp":"ネビトのブーツ","icon":"AR_Boots_G3_006.png","top":["0,0.3880%,10-2","7,0.3880%,10-2"]},{"id":200430007,"ko":"테르시의 부츠","jp":"テルシのブーツ","icon":"AR_Boots_G3_007.png","top":["0,0.3880%,10-2","7,0.3880%,10-2"]},{"id":200430008,"ko":"칼리에의 부츠","jp":"カリエのブーツ","icon":"AR_Boots_G3_008.png","top":["0,0.3880%,10-2","7,0.3880%,10-2"]},{"id":200430009,"ko":"잊혀진 영웅의 부츠","jp":"忘れられた英雄のブーツ","icon":"AR_Boots_G3_009.png","top":["0,0.3880%,10-2","7,0.3880%,10-2"]},{"id":200440007,"ko":"크론비스트의 부츠","jp":"クローンビーストブーツ","icon":"AR_Boots_G4_007.png","top":["9,0.4269%,10-2"]},{"id":200440009,"ko":"심판의 부츠","jp":"ジャッジメントブーツ","icon":"AR_Boots_G4_009.png","top":["7,0.5821%,10-2"]},{"id":200440010,"ko":"둠 플레이트 부츠","jp":"ドゥームプレートブーツ","icon":"AR_Boots_G4_010.png","top":["7,0.5821%,10-2"]},{"id":200440011,"ko":"혼돈의 부츠","jp":"混沌のブーツ","icon":"AR_Boots_G4_011.png","top":["7,0.5821%,10-2"]},{"id":200530005,"ko":"폴리네의 투구","jp":"ポリーネのヘルム","icon":"AR_Helmet_G3_005.png","top":["0,0.3880%,10-2","7,0.3880%,10-2"]},{"id":200530006,"ko":"네비트의 헬멧","jp":"ネビトのヘルム","icon":"AR_Helmet_G3_006.png","top":["0,0.3880%,10-2","7,0.3880%,10-2"]},{"id":200530007,"ko":"테르시의 서클릿","jp":"テルシのサークレット","icon":"AR_Helmet_G3_007.png","top":["0,0.3880%,10-2","7,0.3880%,10-2"]},{"id":200530008,"ko":"악마의 투구","jp":"デーモンヘルム","icon":"AR_Helmet_G3_008.png","top":["0,0.3880%,10-2","5,0.3880%,10-2"]},{"id":200540006,"ko":"심판의 투구","jp":"ジャッジメントヘルム","icon":"AR_Helmet_G4_006.png","top":["7,0.5821%,10-2"]},{"id":200540007,"ko":"둠 플레이트 투구","jp":"ドゥームプレートヘルム","icon":"AR_Helmet_G4_007.png","top":["7,0.5821%,10-2"]},{"id":200540008,"ko":"키리츠의 투구","jp":"キリッツのヘルム","icon":"AR_Helmet_G4_008.png","top":["7,0.5821%,10-2"]},{"id":200630001,"ko":"드래곤의 비늘","jp":"ドラゴンの鱗","icon":"AR_Cape_G3_005.png","top":["0,0.3880%,10-2","5,0.3880%,10-2"]},{"id":200630004,"ko":"여왕개미의 날개","jp":"クイーンアントウィング","icon":"AR_Cape_G3_002.png","top":["0,0.3880%,10-2","5,0.3880%,10-2"]},{"id":200630006,"ko":"아이기스 망토","jp":"アイギスクローク","icon":"AR_Cape_G3_006.png","top":["0,0.3880%,10-2","5,0.3880%,10-2"]},{"id":200630007,"ko":"권능의 망토","jp":"権能のクローク","icon":"AR_Cape_G3_007.png","top":["0,0.3880%,10-2","5,0.3880%,10-2"]},{"id":200630009,"ko":"신록의 망토","jp":"新緑のクローク","icon":"AR_Cape_G3_009.png","top":["0,0.3880%,10-2","5,0.3880%,10-2"]},{"id":200640009,"ko":"암살자의 망토","jp":"アサシンクローク","icon":"AR_Cape_G4_009.png","top":["7,0.5821%,10-2"]},{"id":200640010,"ko":"탐욕의 망토","jp":"貪欲のクローク","icon":"AR_Cape_G4_010.png","top":["7,0.5821%,10-2"]},{"id":200640011,"ko":"혼돈의 망토","jp":"混沌のクローク","icon":"AR_Cape_G4_011.png","top":["7,0.5821%,10-2"]},{"id":200640012,"ko":"감시자의 날개","jp":"監視者の翼","icon":"AR_Cape_G4_012.png","top":["7,0.5821%,10-2"]},{"id":300140001,"ko":"판 드라이드의 목걸이","jp":"パンドライドネックレス","icon":"ACC_Necklace_G4_004.png","top":["5,0.4269%,10-2"]},{"id":300140002,"ko":"사령 템페스트의 목걸이","jp":"死霊テンペストのネックレス","icon":"ACC_Necklace_G4_003.png","top":["5,0.4269%,10-2"]},{"id":300140003,"ko":"블랙 릴리의 마력 목걸이","jp":"ブラックリリーのソーサリーネックレス","icon":"ACC_Necklace_G4_002.png","top":["5,0.4269%,10-2"]},{"id":300140004,"ko":"체르투바의 영혼 목걸이","jp":"チェルトゥバのソウルネックレス","icon":"ACC_Necklace_G4_001.png","top":["5,0.4269%,10-2"]},{"id":300140007,"ko":"인어의 눈물","jp":"マーメイドティアーズ","icon":"ACC_Necklace_G4_010.png","top":["5,0.4269%,10-2"]},{"id":300140008,"ko":"아쿠아스톤 네크리스","jp":"アクアストーンネックレス","icon":"ACC_Necklace_G4_008.png","top":["5,0.4269%,10-2"]},{"id":300140010,"ko":"사제의 목걸이","jp":"プリーストネックレス","icon":"ACC_Necklace_G4_011.png","top":["5,0.4269%,10-2"]},{"id":300240004,"ko":"망상의 귀걸이","jp":"妄想のイヤリング","icon":"ACC_Earring_G4_004.png","top":["5,0.4269%,10-2"]},{"id":300340001,"ko":"인페르노 링","jp":"インフェルノリング","icon":"ACC_Ring_G4_008.png","top":["5,0.4269%,10-2"]},{"id":300340002,"ko":"오만의 반지","jp":"傲慢のリング","icon":"ACC_Ring_G4_007.png","top":["5,0.4269%,10-2"]},{"id":300340009,"ko":"근위대의 반지","jp":"近衛隊のリング","icon":"ACC_Ring_G4_009.png","top":["5,0.4269%,10-2"]},{"id":300340010,"ko":"축복의 반지","jp":"ブレッシングリング","icon":"ACC_Ring_G4_010.png","top":["5,0.4269%,10-2"]},{"id":300340011,"ko":"아쿠아스톤 링","jp":"アクアストーンリング","icon":"ACC_Ring_G4_011.png","top":["5,0.4269%,10-2"]},{"id":300340013,"ko":"마염의 반지","jp":"マジックフレイムリング","icon":"ACC_Ring_G4_013.png","top":["5,0.4269%,10-2"]},{"id":300440003,"ko":"베히모스 가죽 벨트","jp":"ベヒモスレザーベルト","icon":"ACC_Belt_G4_003.png","top":["5,0.4269%,10-2"]},{"id":300440004,"ko":"아다만타이트 벨트","jp":"アダマンタイトベルト","icon":"ACC_Belt_G4_004.png","top":["5,0.4269%,10-2"]},{"id":300440006,"ko":"마염의 벨트","jp":"マジックフレイムベルト","icon":"ACC_Belt_G4_006.png","top":["5,0.4269%,10-2"]},{"id":100110001,"ko":"결정체 (각인) 270000~330000개","jp":"","icon":"WP_Sword_G1_001.png","top":["0,5.7819%,10-2"]},{"id":100110001,"ko":"고급 결정체 (각인) 1800~2200개","jp":"","icon":"WP_Sword_G1_001.png","top":["0,5.7819%,10-2"]},{"id":500313003,"ko":"전투 기술서 (윌 오브 아이언)","jp":"戦闘技術書(ウィル·オブ·アイアン)","icon":"Item_Usable_SkillBook_Sword_04.png","top":["0,0.3880%,10-2"]},{"id":500323002,"ko":"이도류 비전서 (소닉 블래스터)","jp":"二刀流秘伝書(ソニックブラスター)","icon":"Item_Usable_SkillBook_Dual_04.png","top":["0,0.3880%,10-2"]},{"id":500333003,"ko":"암살 비급 (쉐도우 블레이드)","jp":"暗殺秘本(シャドーブレード)","icon":"Item_Usable_SkillBook_Dagger_04.png","top":["0,0.3880%,10-2"]},{"id":500343004,"ko":"궁술 교본 (마나 리게인)","jp":"弓術教本(マナリゲイン)","icon":"Item_Usable_SkillBook_Bow_04.png","top":["0,0.3880%,10-2"]},{"id":500353002,"ko":"마도서 (캔슬)","jp":"魔導書(キャンセル)","icon":"Item_Usable_SkillBook_Staff_04.png","top":["0,0.3880%,10-2"]},{"id":500363004,"ko":"사제의 기록 (임프로브드 오브)","jp":"司祭録(インプルーブオーブ）","icon":"Item_Usable_SkillBook_Orb_04.png","top":["0,0.3880%,10-2"]},{"id":500373004,"ko":"창술서 (바이탈 디스트럭션)","jp":"槍術書(バイタルディストラクション)","icon":"Item_Usable_SkillBook_Spear_04.png","top":["0,0.3880%,10-2"]},{"id":500373006,"ko":"창술서 (디스암)","jp":"槍術書(ディスアーム)","icon":"Item_Usable_SkillBook_Spear_04.png","top":["0,0.3880%,10-2"]},{"id":500383001,"ko":"대검 전술서 (배쉬 Ⅲ)","jp":"両手剣戦術書(バッシュⅢ)","icon":"Item_Usable_SkillBook_GreatSword_04.png","top":["0,0.3880%,10-2"]},{"id":100110001,"ko":"대검 전술서 (체인 소드)","jp":"","icon":"WP_Sword_G1_001.png","top":["0,0.3880%,10-2"]},{"id":500393010,"ko":"석궁 훈련서 (백 텀블링)","jp":"クロスボウ訓練書(バックフリップ)","icon":"Item_Usable_SkillBook_CrossBow_04.png","top":["0,0.3880%,10-2"]},{"id":503293006,"ko":"마검 비술서 (러스트)","jp":"魔剣秘術書(ラスト)","icon":"Item_Usable_SkillBook_ChainSword_04.png","top":["0,0.3880%,10-2"]},{"id":503203007,"ko":"세검 지도서 (트레이스리스)","jp":"細身剣指導書(トレイスレス)","icon":"Item_Usable_SkillBook_Rapier_04.png","top":["0,0.3880%,10-2"]},{"id":503213010,"ko":"마법 공학서 (블래스트 밤 Ⅱ)","jp":"","icon":"Item_Usable_SkillBook_MagicCannon_04.png","top":["0,0.3880%,10-2"]}]