{"tokens": [{"token": "<", "token_id": 27, "type": "input", "position": 0}, {"token": "page", "token_id": 7700, "type": "input", "position": 1}, {"token": ">", "token_id": 29, "type": "input", "position": 2}, {"token": "\n", "token_id": 198, "type": "input", "position": 3}, {"token": " ", "token_id": 220, "type": "input", "position": 4}, {"token": " <", "token_id": 1279, "type": "input", "position": 5}, {"token": "title", "token_id": 7839, "type": "input", "position": 6}, {"token": ">", "token_id": 29, "type": "input", "position": 7}, {"token": "Ant", "token_id": 13217, "type": "input", "position": 8}, {"token": "ich", "token_id": 488, "type": "input", "position": 9}, {"token": "rist", "token_id": 1585, "type": "input", "position": 10}, {"token": "</", "token_id": 3556, "type": "input", "position": 11}, {"token": "title", "token_id": 7839, "type": "input", "position": 12}, {"token": ">", "token_id": 29, "type": "input", "position": 13}, {"token": "\n", "token_id": 198, "type": "input", "position": 14}, {"token": " ", "token_id": 220, "type": "input", "position": 15}, {"token": " <", "token_id": 1279, "type": "input", "position": 16}, {"token": "id", "token_id": 312, "type": "input", "position": 17}, {"token": ">", "token_id": 29, "type": "input", "position": 18}, {"token": "8", "token_id": 23, "type": "input", "position": 19}, {"token": "65", "token_id": 2996, "type": "input", "position": 20}, {"token": "</", "token_id": 3556, "type": "input", "position": 21}, {"token": "id", "token_id": 312, "type": "input", "position": 22}, {"token": ">", "token_id": 29, "type": "input", "position": 23}, {"token": "\n", "token_id": 198, "type": "input", "position": 24}, {"token": " ", "token_id": 220, "type": "input", "position": 25}, {"token": " <", "token_id": 1279, "type": "input", "position": 26}, {"token": "re", "token_id": 260, "type": "input", "position": 27}, {"token": "vision", "token_id": 10178, "type": "input", "position": 28}, {"token": ">", "token_id": 29, "type": "input", "position": 29}, {"token": "\n", "token_id": 198, "type": "input", "position": 30}, {"token": " ", "token_id": 220, "type": "input", "position": 31}, {"token": " ", "token_id": 220, "type": "input", "position": 32}, {"token": " ", "token_id": 220, "type": "input", "position": 33}, {"token": " <", "token_id": 1279, "type": "input", "position": 34}, {"token": "id", "token_id": 312, "type": "input", "position": 35}, {"token": ">", "token_id": 29, "type": "input", "position": 36}, {"token": "15", "token_id": 1314, "type": "input", "position": 37}, {"token": "900", "token_id": 12865, "type": "input", "position": 38}, {"token": "676", "token_id": 42548, "type": "input", "position": 39}, {"token": "</", "token_id": 3556, "type": "input", "position": 40}, {"token": "id", "token_id": 312, "type": "input", "position": 41}, {"token": ">", "token_id": 29, "type": "input", "position": 42}, {"token": "\n", "token_id": 198, "type": "input", "position": 43}, {"token": " ", "token_id": 220, "type": "input", "position": 44}, {"token": " ", "token_id": 220, "type": "input", "position": 45}, {"token": " ", "token_id": 220, "type": "input", "position": 46}, {"token": " <", "token_id": 1279, "type": "input", "position": 47}, {"token": "tim", "token_id": 16514, "type": "input", "position": 48}, {"token": "estamp", "token_id": 27823, "type": "input", "position": 49}, {"token": ">", "token_id": 29, "type": "input", "position": 50}, {"token": "2002", "token_id": 16942, "type": "input", "position": 51}, {"token": "-", "token_id": 12, "type": "input", "position": 52}, {"token": "08", "token_id": 2919, "type": "input", "position": 53}, {"token": "-", "token_id": 12, "type": "input", "position": 54}, {"token": "03", "token_id": 3070, "type": "input", "position": 55}, {"token": "T", "token_id": 51, "type": "input", "position": 56}, {"token": "18", "token_id": 1507, "type": "input", "position": 57}, {"token": ":", "token_id": 25, "type": "input", "position": 58}, {"token": "14", "token_id": 1415, "type": "input", "position": 59}, {"token": ":", "token_id": 25, "type": "input", "position": 60}, {"token": "12", "token_id": 1065, "type": "input", "position": 61}, {"token": "Z", "token_id": 57, "type": "input", "position": 62}, {"token": "</", "token_id": 3556, "type": "input", "position": 63}, {"token": "tim", "token_id": 16514, "type": "input", "position": 64}, {"token": "estamp", "token_id": 27823, "type": "input", "position": 65}, {"token": ">", "token_id": 29, "type": "input", "position": 66}, {"token": "\n", "token_id": 198, "type": "input", "position": 67}, {"token": " ", "token_id": 220, "type": "input", "position": 68}, {"token": " ", "token_id": 220, "type": "input", "position": 69}, {"token": " ", "token_id": 220, "type": "input", "position": 70}, {"token": " <", "token_id": 1279, "type": "input", "position": 71}, {"token": "cont", "token_id": 3642, "type": "input", "position": 72}, {"token": "ribut", "token_id": 2455, "type": "input", "position": 73}, {"token": "or", "token_id": 273, "type": "input", "position": 74}, {"token": ">", "token_id": 29, "type": "input", "position": 75}, {"token": "\n", "token_id": 198, "type": "input", "position": 76}, {"token": " ", "token_id": 220, "type": "input", "position": 77}, {"token": " ", "token_id": 220, "type": "input", "position": 78}, {"token": " ", "token_id": 220, "type": "input", "position": 79}, {"token": " ", "token_id": 220, "type": "input", "position": 80}, {"token": " ", "token_id": 220, "type": "input", "position": 81}, {"token": " <", "token_id": 1279, "type": "input", "position": 82}, {"token": "username", "token_id": 29460, "type": "input", "position": 83}, {"token": ">", "token_id": 29, "type": "input", "position": 84}, {"token": "Paris", "token_id": 40313, "type": "input", "position": 85}, {"token": "</", "token_id": 3556, "type": "input", "position": 86}, {"token": "username", "token_id": 29460, "type": "input", "position": 87}, {"token": ">", "token_id": 29, "type": "input", "position": 88}, {"token": "\n", "token_id": 198, "type": "input", "position": 89}, {"token": " ", "token_id": 220, "type": "input", "position": 90}, {"token": " ", "token_id": 220, "type": "input", "position": 91}, {"token": " ", "token_id": 220, "type": "input", "position": 92}, {"token": " ", "token_id": 220, "type": "input", "position": 93}, {"token": " ", "token_id": 220, "type": "input", "position": 94}, {"token": " <", "token_id": 1279, "type": "input", "position": 95}, {"token": "id", "token_id": 312, "type": "input", "position": 96}, {"token": ">", "token_id": 29, "type": "input", "position": 97}, {"token": "23", "token_id": 1954, "type": "input", "position": 98}, {"token": "</", "token_id": 3556, "type": "input", "position": 99}, {"token": "id", "token_id": 312, "type": "input", "position": 100}, {"token": ">", "token_id": 29, "type": "input", "position": 101}, {"token": "\n", "token_id": 198, "type": "input", "position": 102}, {"token": " ", "token_id": 220, "type": "input", "position": 103}, {"token": " ", "token_id": 220, "type": "input", "position": 104}, {"token": " ", "token_id": 220, "type": "input", "position": 105}, {"token": " </", "token_id": 7359, "type": "input", "position": 106}, {"token": "cont", "token_id": 3642, "type": "input", "position": 107}, {"token": "ribut", "token_id": 2455, "type": "input", "position": 108}, {"token": "or", "token_id": 273, "type": "input", "position": 109}, {"token": ">", "token_id": 29, "type": "input", "position": 110}, {"token": "\n", "token_id": 198, "type": "input", "position": 111}, {"token": " ", "token_id": 220, "type": "input", "position": 112}, {"token": " ", "token_id": 220, "type": "input", "position": 113}, {"token": " ", "token_id": 220, "type": "input", "position": 114}, {"token": " <", "token_id": 1279, "type": "input", "position": 115}, {"token": "min", "token_id": 1084, "type": "input", "position": 116}, {"token": "or", "token_id": 273, "type": "input", "position": 117}, {"token": " />", "token_id": 11037, "type": "input", "position": 118}, {"token": "\n", "token_id": 198, "type": "input", "position": 119}, {"token": " ", "token_id": 220, "type": "input", "position": 120}, {"token": " ", "token_id": 220, "type": "input", "position": 121}, {"token": " ", "token_id": 220, "type": "input", "position": 122}, {"token": " <", "token_id": 1279, "type": "input", "position": 123}, {"token": "comment", "token_id": 23893, "type": "input", "position": 124}, {"token": ">", "token_id": 29, "type": "input", "position": 125}, {"token": "Autom", "token_id": 38062, "type": "input", "position": 126}, {"token": "ated", "token_id": 515, "type": "input", "position": 127}, {"token": " conversion", "token_id": 11315, "type": "input", "position": 128}, {"token": "</", "token_id": 3556, "type": "input", "position": 129}, {"token": "comment", "token_id": 23893, "type": "input", "position": 130}, {"token": ">", "token_id": 29, "type": "input", "position": 131}, {"token": "\n", "token_id": 198, "type": "input", "position": 132}, {"token": " ", "token_id": 220, "type": "input", "position": 133}, {"token": " ", "token_id": 220, "type": "input", "position": 134}, {"token": " ", "token_id": 220, "type": "input", "position": 135}, {"token": " <", "token_id": 1279, "type": "input", "position": 136}, {"token": "text", "token_id": 5239, "type": "input", "position": 137}, {"token": " xml", "token_id": 35555, "type": "input", "position": 138}, {"token": ":", "token_id": 25, "type": "input", "position": 139}, {"token": "space", "token_id": 13200, "type": "input", "position": 140}, {"token": "=\"", "token_id": 2625, "type": "input", "position": 141}, {"token": "pres", "token_id": 18302, "type": "input", "position": 142}, {"token": "erve", "token_id": 3760, "type": "input", "position": 143}, {"token": "\">", "token_id": 5320, "type": "input", "position": 144}, {"token": "#", "token_id": 2, "type": "input", "position": 145}, {"token": "RED", "token_id": 22083, "type": "input", "position": 146}, {"token": "I", "token_id": 40, "type": "input", "position": 147}, {"token": "RECT", "token_id": 23988, "type": "input", "position": 148}, {"token": " [[", "token_id": 16410, "type": "input", "position": 149}, {"token": "Christian", "token_id": 20298, "type": "input", "position": 150}, {"token": "ity", "token_id": 414, "type": "input", "position": 151}, {"token": "]]", "token_id": 11907, "type": "input", "position": 152}, {"token": "</", "token_id": 3556, "type": "input", "position": 153}, {"token": "text", "token_id": 5239, "type": "input", "position": 154}, {"token": ">", "token_id": 29, "type": "input", "position": 155}, {"token": "\n", "token_id": 198, "type": "input", "position": 156}, {"token": " ", "token_id": 220, "type": "input", "position": 157}, {"token": " </", "token_id": 7359, "type": "input", "position": 158}, {"token": "re", "token_id": 260, "type": "input", "position": 159}, {"token": "vision", "token_id": 10178, "type": "input", "position": 160}, {"token": ">", "token_id": 29, "type": "input", "position": 161}, {"token": "\n", "token_id": 198, "type": "input", "position": 162}, {"token": "</", "token_id": 3556, "type": "input", "position": 163}, {"token": "page", "token_id": 7700, "type": "input", "position": 164}, {"token": ">", "token_id": 29, "type": "input", "position": 165}], "factors": [[[0.0, 0.006464368663728237, 0.0, 0.4438666105270386, 0.0, 0.011111454106867313, 0.0, 0.0, 0.0048598311841487885, 0.0021253463346511126, 0.002021806314587593, 0.0, 0.0, 0.0, 0.4028240442276001, 0.0, 0.002033619675785303, 0.0, 0.0, 0.0, 0.0, 0.0, 0.0, 0.0, 0.3981578052043915, 0.0, 0.0, 0.0, 0.0, 0.0, 0.4015658497810364, 0.0, 0.0, 0.0, 0.0, 0.0, 0.0, 0.0, 0.011933413334190845, 0.0016796669224277139, 0.011456573382019997, 0.005070708692073822, 0.012865344993770123, 0.33872440457344055, 0.004511360544711351, 0.0, 0.0, 0.0, 0.0, 0.0, 0.0, 0.0, 0.000637640303466469, 0.0, 0.0, 0.0, 0.0, 0.0, 0.019031807780265808, 0.0, 0.029742268845438957, 0.0, 0.0, 0.0, 0.0, 0.0, 0.0, 0.3402463495731354, 0.003843082347884774, 0.0, 0.0, 0.0, 0.0, 0.0, 0.0, 0.003866860643029213, 0.34656649827957153, 0.0, 0.0, 0.0, 0.0, 0.0, 0.0, 0.0, 0.0, 0.009546739980578423, 0.0, 0.007312329951673746, 0.0, 0.329816997051239, 0.013621250167489052, 0.0084784384816885, 0.005200537852942944, 0.00235113687813282, 0.00011259898747084662, 0.0, 0.0, 0.0, 0.0, 0.0, 0.002806582488119602, 0.014288857579231262, 0.3017636835575104, 0.007317070849239826, 0.00080348108895123, 0.0, 0.0, 0.0, 0.0, 0.020715339109301567, 0.010882088914513588, 0.33011943101882935, 0.00616624066606164, 0.002498957561329007, 0.0, 0.0018100590677931905, 0.0, 0.0, 0.008275564759969711, 0.33037468791007996, 0.012252386659383774, 0.006276315543800592, 0.001270798733457923, 0.0, 0.0, 0.0, 0.01146695576608181, 0.012273339554667473, 0.00832842756062746, 0.0, 0.0, 0.0, 0.3144199252128601, 0.014668365940451622, 0.0060534304939210415, 0.0007562942919321358, 0.0, 0.0, 0.0, 0.02973322570323944, 0.0, 0.0, 0.0, 0.0, 0.0, 0.021049587056040764, 0.002831679070368409, 0.0035109976306557655, 0.0006675359909422696, 0.020510030910372734, 0.0, 0.0, 0.0, 0.0, 0.001111225807107985, 0.0, 0.31650662422180176, 0.009325276128947735, 0.006336343940347433, 0.004635926801711321, 0.0, 0.005480905529111624, 0.3126155138015747, 0.008014971390366554, 0.0, 0.008280625566840172], [0.0, 0.01854260079562664, 0.0, 0.0, 0.0, 0.0, 0.2352755218744278, 0.0, 0.0, 0.0, 0.0, 0.0, 0.7785732746124268, 0.0, 0.0, 0.0, 0.018383212387561798, 0.3884821832180023, 0.008585426956415176, 0.0, 0.0, 0.14509664475917816, 1.066015601158142, 0.006691846996545792, 0.02086632512509823, 0.0, 0.003165119094774127, 0.032899096608161926, 0.1107868105173111, 0.0, 0.01867438107728958, 0.0, 0.0, 0.0, 0.0, 0.6027271747589111, 0.02994883805513382, 0.0, 0.15891943871974945, 0.05651434510946274, 0.16486072540283203, 1.1097347736358643, 0.12363137304782867, 0.05639197677373886, 0.09773470461368561, 0.09064497798681259, 0.08956369012594223, 0.00960275623947382, 0.019753431901335716, 0.20567503571510315, 0.0, 0.0, 0.0, 0.08234471082687378, 0.0, 0.010761204175651073, 0.0, 0.0, 0.0, 0.0, 0.0, 0.003039042465388775, 0.03330221027135849, 0.013398689217865467, 0.6049431562423706, 0.8855863809585571, 0.01687435247004032, 0.006804897915571928, 0.0, 0.03184648975729942, 0.05019873008131981, 0.0, 0.0, 0.04152022302150726, 0.1954466849565506, 0.0, 0.0, 0.0, 0.0, 0.0, 0.0, 0.025222504511475563, 0.0, 0.24973751604557037, 0.00473452266305685, 0.0, 0.08547616750001907, 0.8243059515953064, 0.010641941800713539, 0.030338145792484283, 0.06923376768827438, 0.08068423718214035, 0.0891999676823616, 0.09509079903364182, 0.10016649216413498, 0.0, 0.5255578756332397, 0.024205515161156654, 0.0, 0.18641099333763123, 1.1879546642303467, 0.16623368859291077, 0.08542455732822418, 0.1781378835439682, 0.17173290252685547, 0.16739961504936218, 0.0, 0.30556464195251465, 0.4783661663532257, 0.6010943651199341, 0.004051394294947386, 0.0, 0.0, 0.0, 0.011809558607637882, 0.0, 0.04013233259320259, 0.1723477691411972, 0.0, 0.0, 0.06808378547430038, 0.06544412672519684, 0.05705903097987175, 0.022720878943800926, 0.10097957402467728, 0.0, 0.0, 0.0, 0.0, 0.005930984392762184, 0.708152711391449, 0.02529837191104889, 0.0, 0.08803972601890564, 0.10702534019947052, 0.12670552730560303, 0.009620973840355873, 0.12350884824991226, 0.0, 0.0, 0.035077109932899475, 0.0, 0.0, 0.043362826108932495, 0.0, 0.0, 0.0, 0.0, 0.0, 0.0, 0.0, 0.0025034344289451838, 0.0, 0.0, 0.696934163570404, 0.0, 0.0, 0.04451286420226097, 0.0, 0.24937736988067627, 0.4833119809627533, 0.012577967718243599, 0.0, 0.0, 0.43028032779693604, 0.0], [0.0, 0.0, 0.0, 0.0, 0.39475181698799133, 0.01923738233745098, 0.0, 0.0, 0.057139672338962555, 0.010830461047589779, 0.0023903092369437218, 0.0, 0.0, 0.0, 0.0, 0.43288806080818176, 0.0, 0.0, 0.0, 0.034435950219631195, 0.011794949881732464, 0.0034961409401148558, 0.0, 0.0, 0.008674495853483677, 0.4732692837715149, 0.0, 0.0, 0.0, 0.0, 0.0, 0.4653921127319336, 0.49072933197021484, 0.5241474509239197, 0.0, 0.03073044680058956, 0.0019909413531422615, 0.0549796000123024, 0.048360805958509445, 0.026417456567287445, 0.022846506908535957, 0.03535071015357971, 0.04512153938412666, 0.06473331153392792, 0.5388015508651733, 0.5472843050956726, 0.5505967140197754, 0.015161902643740177, 0.027478419244289398, 0.0, 0.0, 0.02391519583761692, 0.0, 0.0005632314132526517, 0.0, 0.0, 0.0, 0.0, 0.0, 0.0, 0.0, 0.0, 0.007251158356666565, 0.015618951991200447, 0.010016710497438908, 0.0, 0.005072572734206915, 0.029216952621936798, 0.5008241534233093, 0.5311938524246216, 0.5404568910598755, 0.0079141641035676, 0.0, 0.0, 0.0, 0.00569590600207448, 0.0, 0.47445133328437805, 0.4956844747066498, 0.5206224322319031, 0.5355189442634583, 0.541049599647522, 0.004011926241219044, 0.0, 0.0, 0.022781694307923317, 0.0, 0.00118253193795681, 0.006518031936138868, 0.034440796822309494, 0.5163654685020447, 0.5270453691482544, 0.5343432426452637, 0.5367869734764099, 0.5364956855773926, 0.0, 0.017682846635580063, 0.00579599617049098, 0.015062817372381687, 0.025586087256669998, 0.028827417641878128, 0.05300528556108475, 0.07819843292236328, 0.5250941514968872, 0.5392313003540039, 0.5385741591453552, 0.0, 0.006233868654817343, 0.0, 0.0029951019678264856, 0.018568160012364388, 0.00797964259982109, 0.482860267162323, 0.517133891582489, 0.5244051218032837, 0.003832824295386672, 0.010549312457442284, 0.0, 0.011917724274098873, 0.038615938276052475, 0.5055198073387146, 0.5171945095062256, 0.5213911533355713, 0.0050682430155575275, 0.0, 0.0, 0.03886241838335991, 0.0, 0.0, 0.008915796875953674, 0.0, 0.0, 0.014500654302537441, 0.5007147789001465, 0.5193176865577698, 0.5268864035606384, 0.0009306299616582692, 0.0, 0.0, 0.0, 0.0, 0.0, 0.0, 0.0, 0.0, 0.03312210366129875, 0.0, 0.007538288831710815, 0.0, 0.0, 0.008339513093233109, 0.0, 0.0, 0.0, 0.0, 0.0, 0.002321123145520687, 0.4946795701980591, 0.0, 0.00994716864079237, 0.0, 0.012309201061725616, 7.837805242161267e-06, 0.0, 0.0, 0.0033072789665311575], [0.0, 0.0, 0.0, 0.0, 0.0008595594554208219, 0.767516553401947, 0.02979937754571438, 0.0, 0.0, 0.0, 0.0, 0.03368016704916954, 0.0, 0.0, 0.0, 0.013803597539663315, 1.0418493747711182, 0.09211795032024384, 0.012117707170546055, 0.0, 0.0, 0.0, 0.0, 0.0, 0.0, 0.0, 1.0264991521835327, 0.13766244053840637, 0.0, 0.00912614818662405, 0.0, 0.0, 0.0, 0.001031724619679153, 1.0474529266357422, 0.10206890106201172, 0.020609285682439804, 0.0, 0.0, 0.0, 0.0, 0.0, 0.0, 0.0, 0.0, 0.0, 0.0010302145965397358, 0.9721589684486389, 0.01813795603811741, 0.0012192277936264873, 0.0, 0.0, 0.012960035353899002, 0.0, 0.004668776411563158, 0.0, 0.0, 0.0, 0.0018268406856805086, 0.00023700362362433225, 0.01032964512705803, 0.0006541676702909172, 0.0, 0.0, 0.0, 0.0, 0.0, 0.0, 0.0, 0.010310045443475246, 0.019346343353390694, 0.9759653806686401, 0.07153593003749847, 0.0, 0.02134791761636734, 0.021249540150165558, 0.004128557629883289, 0.0004117225471418351, 0.015520775690674782, 0.026273973286151886, 0.03143136575818062, 0.033941663801670074, 1.0246671438217163, 0.04305780678987503, 0.03661377355456352, 0.0, 0.007902123965322971, 0.0, 0.004186087753623724, 0.0, 0.0, 0.0, 0.0, 0.006352298427373171, 0.0138252479955554, 1.050706148147583, 0.12770450115203857, 0.04242662712931633, 0.0, 0.0, 0.0, 0.0, 0.0, 0.0, 0.0, 0.0, 0.4018121063709259, 0.05923677608370781, 0.0, 0.0, 0.026007216423749924, 0.020059430971741676, 0.0040718973614275455, 0.01424300204962492, 0.021861199289560318, 1.011763572692871, 0.08469190448522568, 0.058997560292482376, 0.0, 0.0, 0.0, 0.0, 0.0, 0.9910601377487183, 0.026662789285182953, 0.009520800784230232, 0.0, 0.0, 0.0, 0.006421977188438177, 0.0, 0.0, 0.0, 0.0, 0.0, 0.0, 0.9676930904388428, 0.07802370190620422, 0.0665651187300682, 0.12480336427688599, 0.0, 0.156209334731102, 0.0, 0.0, 0.013759845867753029, 0.0542379766702652, 0.0, 0.0, 0.0, 0.1841050535440445, 0.0, 0.0, 0.0, 0.08972205221652985, 0.0, 0.0, 0.0, 0.0, 0.4101566970348358, 0.10175991803407669, 0.0, 0.0008731845300644636, 0.009809084236621857, 0.3160425126552582, 0.0, 0.007265207823365927], [1.8510334491729736, 0.001905654789879918, 0.000381127349101007, 0.007317923940718174, 0.0004322360618971288, 0.001890395418740809, 0.0, 0.005038192495703697, 0.001464793924242258, 0.003907561767846346, 0.0011059172684326768, 0.0, 0.0, 0.0, 0.0, 0.0, 0.0, 0.0, 0.0015547741204500198, 0.0, 0.0, 0.0, 0.0, 0.0, 0.0, 0.0, 0.0, 0.0, 0.0, 0.0, 0.0, 0.0, 0.0, 0.0, 0.0, 0.0, 0.0, 0.0, 0.0, 0.0, 0.0, 0.0, 0.0, 0.0, 0.0, 0.0, 0.0, 0.0, 0.0, 0.0, 0.0, 0.0, 0.0, 0.0, 0.0033894884400069714, 0.0, 0.0018496387638151646, 0.0009535029530525208, 0.0015353988856077194, 0.0, 0.002328040311113, 0.0, 0.0, 0.0, 0.0, 0.0, 0.0, 0.0, 0.0, 0.0, 0.0, 0.0011454116320237517, 0.0, 0.0, 0.0, 0.0, 0.0014483083505183458, 0.0, 0.0, 0.0, 0.0, 0.0, 0.0, 0.0, 0.0024232869036495686, 0.0028171169105917215, 0.0, 0.0, 0.0, 0.0, 0.0, 0.0, 0.0, 0.0, 0.0, 0.0004978408105671406, 0.0, 0.0, 0.0, 0.0, 0.0, 0.0, 0.0, 0.0, 0.0, 0.0, 0.0, 0.0, 0.0, 0.00011854671902256086, 0.0, 0.0001801370526663959, 0.0, 0.0, 0.0, 0.0006347002927213907, 0.0, 0.0, 0.0, 0.0, 0.0, 0.0, 0.0, 0.00016250061162281781, 0.0, 0.0, 0.0011478897649794817, 0.008955859579145908, 0.00695296423509717, 0.0003922627365682274, 0.0, 0.0, 0.0, 0.0, 0.0, 0.0, 0.0022853182163089514, 0.0, 0.0, 0.0, 0.0, 0.0, 0.0, 0.002088511362671852, 0.0, 0.0012887686025351286, 0.0, 0.0, 9.435493120690808e-05, 0.0052910977974534035, 0.0026423009112477303, 0.004955485463142395, 0.0012693050084635615, 0.0, 0.0, 0.0, 0.0, 0.0, 0.0, 0.0, 0.0, 0.0, 0.0, 0.0, 0.0, 0.0], [0.0, 0.4620749354362488, 0.08937560766935349, 0.0, 0.1483452171087265, 0.10769065469503403, 0.4510524272918701, 0.008159641176462173, 0.3900160789489746, 0.31753331422805786, 0.31206247210502625, 0.02204938419163227, 0.15888692438602448, 0.0, 0.005084451287984848, 0.07976008206605911, 0.003133016638457775, 0.31646084785461426, 0.0, 0.1683240830898285, 0.16508695483207703, 0.0, 0.0051746126264333725, 0.0, 0.0, 0.05083262920379639, 0.0, 0.5211131572723389, 0.4455450177192688, 0.025615885853767395, 0.0, 0.07934946566820145, 0.0582154355943203, 0.03310064226388931, 0.005204562563449144, 0.21745838224887848, 0.0, 0.13056348264217377, 0.11055538058280945, 0.13610544800758362, 0.0, 0.0, 0.0, 0.0, 0.0, 0.0, 0.0, 0.0, 0.557675838470459, 0.40965431928634644, 0.0, 0.1532469540834427, 0.0, 0.0, 0.0, 0.0, 0.0, 0.013611949048936367, 0.0, 0.013494823127985, 0.0, 0.028760557994246483, 0.0950627401471138, 0.0, 0.23624594509601593, 0.0716366097331047, 0.0, 0.0, 0.028297871351242065, 0.0, 0.0, 0.0, 0.6029832363128662, 0.5632492899894714, 0.371209055185318, 0.00812683068215847, 0.0, 0.06117667257785797, 0.03844243660569191, 0.019002551212906837, 0.010028618387877941, 0.0, 0.006209044251590967, 0.4322773516178131, 0.0, 0.3422355353832245, 0.0, 0.09824961423873901, 0.0, 0.0, 0.0, 0.0, 0.0, 0.0, 0.0, 0.0, 0.2390306442975998, 0.0, 0.13887833058834076, 0.0, 0.0, 0.0, 0.0, 0.0, 0.0, 0.0, 0.0728754922747612, 0.39749911427497864, 0.33452603220939636, 0.1405669003725052, 0.0, 0.010160112753510475, 0.0319766029715538, 0.008762763813138008, 0.0, 0.0, 0.5083726048469543, 0.3737030327320099, 0.13089053332805634, 0.014691388234496117, 0.003747851587831974, 0.0, 0.0, 0.0, 0.5572356581687927, 0.0, 0.4439299404621124, 0.33387529850006104, 0.3427988588809967, 0.025570379570126534, 0.2247554212808609, 0.0, 0.019247058779001236, 0.0, 0.0, 0.0, 0.0, 0.4867326319217682, 0.45279166102409363, 0.24824772775173187, 0.4897528886795044, 0.15790733695030212, 0.5830371379852295, 0.3911273777484894, 0.06320445239543915, 0.20806635916233063, 0.45588546991348267, 0.35807979106903076, 0.40210598707199097, 0.20042186975479126, 0.4284241497516632, 0.3588576912879944, 0.20456518232822418, 0.01724705658853054, 0.17739897966384888, 0.004318171180784702, 0.021451514214277267, 0.006276776548475027, 0.036914318799972534, 0.3320981562137604, 0.2590041756629944, 0.0, 0.01710483804345131, 0.04305427893996239, 0.2862265706062317, 0.003608168801292777], [0.0, 0.14626029133796692, 0.648818850517273, 0.10960331559181213, 0.09312991797924042, 0.02088988572359085, 0.000984836369752884, 1.2109887599945068, 0.15433737635612488, 0.17799042165279388, 0.2045612931251526, 0.0, 0.0, 0.34973612427711487, 0.022121364250779152, 0.06879443675279617, 0.0, 0.007982796058058739, 1.5468484163284302, 0.3389051854610443, 0.29671022295951843, 0.0, 0.032479651272296906, 0.347292959690094, 0.0, 0.05789840593934059, 0.0, 0.0, 0.07776100933551788, 1.0004746913909912, 0.0478401742875576, 0.05276106670498848, 0.04560239613056183, 0.032986413687467575, 0.011074027977883816, 0.006207733880728483, 1.5005271434783936, 0.28335246443748474, 0.1154840886592865, 0.10279252380132675, 0.008461536839604378, 0.0, 0.03153478726744652, 0.0, 0.0, 0.0030187764205038548, 0.004221820272505283, 0.04435170441865921, 0.0, 0.09388438612222672, 0.9523403644561768, 0.10542415827512741, 0.312325119972229, 0.0, 0.16032026708126068, 0.0, 0.0, 0.0, 0.04196491464972496, 0.0, 0.04045965522527695, 0.0, 0.0, 0.0, 0.0, 0.022236278280615807, 0.19497354328632355, 0.0030732876621186733, 0.032326292246580124, 0.03105197660624981, 0.014500786550343037, 0.050324324518442154, 0.0, 0.0, 0.09271890670061111, 0.8921115398406982, 0.19337184727191925, 0.04507960006594658, 0.03335066884756088, 0.023782959207892418, 0.014305475167930126, 0.00444374093785882, 0.05819697305560112, 0.0, 1.386669397354126, 0.1583724319934845, 0.02370736189186573, 0.0, 0.15974344313144684, 0.0, 0.0, 0.0, 0.0, 0.0, 0.0, 0.09319457411766052, 0.0143130449578166, 1.4810822010040283, 0.37091314792633057, 0.01742452010512352, 0.0, 0.03477921709418297, 0.0, 0.0, 0.0, 0.0, 0.0, 0.0, 0.0, 0.0, 0.0, 0.0, 0.0, 0.0, 0.0, 0.0, 0.0, 0.01313378382474184, 0.07922091335058212, 0.0, 0.0, 0.0, 0.0, 0.03458075970411301, 0.0, 0.9668076038360596, 0.053567830473184586, 0.11032050102949142, 0.0, 0.0, 0.0, 0.0, 0.0, 0.0, 0.0, 0.0, 0.0, 0.0, 0.0, 0.1665017008781433, 0.0, 0.5984942317008972, 0.0, 0.08120742440223694, 0.3018017113208771, 0.2752915918827057, 0.0018507551867514849, 0.0, 0.05225997790694237, 0.2789623439311981, 0.05541551113128662, 0.06023991107940674, 0.08826987445354462, 0.0, 0.0, 0.0, 0.0, 0.0, 0.0, 0.0, 0.0, 0.0, 0.0, 0.0, 0.0, 0.0], [0.0, 0.010005705989897251, 0.27276158332824707, 0.0, 0.0, 0.007770451717078686, 0.0, 0.16218183934688568, 0.0, 0.0, 0.006576284300535917, 0.0, 0.022272253409028053, 0.4308108687400818, 0.0042467801831662655, 0.0, 0.0, 0.0, 0.022191347554326057, 0.0, 0.0, 0.0, 0.0, 0.4144882559776306, 0.006209707818925381, 0.0, 0.0, 0.0, 0.0, 0.15816712379455566, 0.0, 0.0, 0.0, 0.0, 0.0, 0.0, 0.0, 0.0, 0.0335809551179409, 0.06058923527598381, 0.0, 0.0, 0.49749061465263367, 0.03718993812799454, 0.0, 0.0, 0.0, 0.0, 0.0, 0.0, 0.1576390117406845, 0.0, 0.0, 0.0, 0.0, 0.018581479787826538, 0.0, 0.003323595505207777, 0.0, 0.005913061555474997, 0.0, 0.01920800656080246, 0.07124533504247665, 0.017428571358323097, 0.0, 0.017286239191889763, 0.3988093137741089, 0.01409563235938549, 0.0013307197950780392, 0.0, 0.0, 0.0, 0.0, 0.0, 0.00197733286768198, 0.18790240585803986, 0.0, 0.0, 0.0, 0.0, 0.0, 0.0, 0.0, 0.0, 0.08424250036478043, 0.0019771945662796497, 0.0, 0.03211905434727669, 0.48739510774612427, 0.06513085216283798, 0.019372789189219475, 0.01885967329144478, 0.016309237107634544, 0.013390274718403816, 0.011181555688381195, 0.0, 0.0, 0.0, 0.0, 0.0, 0.0, 0.4807905852794647, 0.07119855284690857, 0.009177428670227528, 0.005962987430393696, 0.005667673423886299, 0.0, 0.0, 0.0, 0.0826166421175003, 0.5214637517929077, 0.07037283480167389, 0.044676151126623154, 0.042072683572769165, 0.04181903228163719, 0.03679325059056282, 0.0, 0.021480735391378403, 0.3246360123157501, 0.05400087311863899, 0.02887234464287758, 0.02973223105072975, 0.03487982228398323, 0.023735299706459045, 0.0, 0.22914385795593262, 0.01388155110180378, 0.04534803703427315, 0.08598629385232925, 0.058046553283929825, 0.010866101831197739, 0.5605782866477966, 0.0843682661652565, 0.02668028511106968, 0.020914897322654724, 0.016318324953317642, 0.045048050582408905, 0.0, 0.039361823350191116, 0.06809872388839722, 0.011166336014866829, 0.0, 0.0, 0.022288048639893532, 0.3519480526447296, 0.05037174001336098, 0.02573433890938759, 0.05130516365170479, 0.04998113214969635, 0.0026618049014359713, 0.015205620788037777, 0.05821877345442772, 0.23772484064102173, 0.028802430257201195, 0.023017389699816704, 0.5572904348373413, 0.08680258691310883, 0.045043837279081345, 0.021323587745428085, 0.0, 0.06489138305187225, 0.5477914214134216, 0.10281691700220108, 0.06072168052196503, 0.05393621325492859, 0.5484969615936279], [0.0, 0.0, 0.0, 0.0, 0.0, 0.010379783809185028, 0.0, 0.0, 0.05066674202680588, 0.10048544406890869, 0.0997450202703476, 0.0, 0.0, 0.0, 0.0, 0.0, 0.0, 0.0, 0.0, 0.36012715101242065, 0.4306700825691223, 0.006522567942738533, 0.051253776997327805, 0.026680316776037216, 0.017790528014302254, 0.010173168033361435, 0.00904017873108387, 0.0, 0.0, 0.0009514164994470775, 0.03360296040773392, 0.00760844349861145, 0.005209994036704302, 0.008988874964416027, 0.019149139523506165, 0.0, 0.05454162508249283, 0.44167959690093994, 0.4028434455394745, 0.4508310556411743, 0.04917564243078232, 0.06116703897714615, 0.0004995940253138542, 0.0, 0.011319231241941452, 0.009130489081144333, 0.011703979223966599, 0.02677721530199051, 0.0086738346144557, 0.03244202584028244, 0.14285558462142944, 0.6283556222915649, 0.8350822329521179, 0.969342827796936, 1.0471981763839722, 0.9738788604736328, 1.0322027206420898, 0.9494264721870422, 1.0177803039550781, 0.9450165033340454, 0.9222934246063232, 0.8444415926933289, 0.5369390249252319, 0.11666931211948395, 0.0, 0.0661347284913063, 0.10056070983409882, 0.05638700723648071, 0.024000637233257294, 0.01288638636469841, 0.004257808905094862, 0.03709857538342476, 0.0, 0.0, 0.0, 0.0, 0.016543034464120865, 0.0, 0.0, 0.0, 0.0026763940695673227, 0.006561313755810261, 0.0, 0.0, 0.0, 0.13140401244163513, 0.0, 0.050649065524339676, 0.0021051056683063507, 0.0004850494733545929, 0.0, 0.0, 0.0, 0.0, 0.0, 0.0, 0.0, 0.04312283545732498, 0.4977008104324341, 0.0, 0.0211795661598444, 0.0, 0.0, 0.0, 0.0, 0.0, 0.0, 0.0, 0.0, 0.0, 0.0, 0.0, 0.0, 0.0, 0.0, 0.0, 0.0, 0.0, 0.012958802282810211, 0.0, 0.0, 0.0, 0.0, 0.0, 0.0, 0.0, 0.019469086080789566, 0.02459905296564102, 0.05730573460459709, 0.0, 0.0, 0.0, 0.0, 0.0, 0.0, 0.0, 0.0, 0.0, 0.0, 0.05802762880921364, 0.038329117000103, 0.06607010960578918, 0.021023135632276535, 0.046938903629779816, 0.0, 0.044030338525772095, 0.08648403733968735, 0.13005894422531128, 0.06491822749376297, 0.019342029467225075, 0.038776446133852005, 0.03446727991104126, 0.030833428725600243, 0.0, 0.0, 0.0, 0.0, 0.0, 0.0, 0.0, 0.0, 0.0, 0.0, 0.0, 0.0, 0.0], [0.0, 0.0, 0.0, 0.04966191202402115, 0.0, 0.0, 0.0, 0.0, 0.0, 0.0, 0.0, 1.7016600370407104, 0.0, 0.0, 0.0, 0.0, 0.0, 0.0, 0.00019955031166318804, 0.0, 0.0, 1.7015950679779053, 0.026120532304048538, 0.0, 0.0, 0.0, 0.0, 0.0, 0.0, 0.0, 0.034204114228487015, 0.0, 0.0, 0.0, 0.0, 0.0, 0.0, 0.0, 0.0, 0.0, 1.4752473831176758, 0.0, 0.0, 0.0, 0.01940007694065571, 0.008486971259117126, 0.0008864760748110712, 0.0, 0.0, 0.0, 0.0, 0.0, 0.08802201598882675, 0.0, 0.08361553400754929, 0.0, 0.0, 0.0, 0.0, 0.0, 0.03386681154370308, 0.0, 0.0, 1.4451892375946045, 0.23230834305286407, 0.07877006381750107, 0.02130965143442154, 0.0, 0.0, 0.0, 0.0, 0.0, 0.0, 0.0, 0.0, 0.0, 0.0, 0.0, 0.0, 0.0, 0.0, 0.0, 0.0, 0.0, 0.015496786683797836, 0.0, 1.718606948852539, 0.05777354538440704, 0.0, 0.0, 0.017076274380087852, 0.005203339271247387, 0.0013902157079428434, 0.0, 0.0, 0.0, 0.0, 0.0, 0.0, 1.631032943725586, 0.05451484024524689, 0.0, 0.0, 0.05876815319061279, 0.048167962580919266, 0.038056645542383194, 0.8408267498016357, 0.10001964867115021, 0.13371552526950836, 0.0, 0.0, 0.0, 0.0, 0.0, 0.0, 0.0, 0.0, 0.0, 0.11858455836772919, 0.0, 0.021237075328826904, 0.012636602856218815, 0.0, 0.013989790342748165, 0.0, 0.0, 0.0, 0.0, 0.024741029366850853, 1.4986048936843872, 0.05495025962591171, 0.0, 0.0, 0.031954213976860046, 0.024324467405676842, 0.027076810598373413, 0.014934925362467766, 0.0, 0.10896602272987366, 0.021769598126411438, 0.010787788778543472, 0.19978298246860504, 0.027367206290364265, 0.0, 0.12620028853416443, 0.084163136780262, 0.0105518763884902, 0.0, 0.0, 0.15774093568325043, 0.0, 0.0, 0.04372477903962135, 1.4957222938537598, 0.043845660984516144, 0.0, 0.0011138301342725754, 0.007899552583694458, 0.8435279726982117, 0.17324039340019226, 0.0, 0.0, 0.0, 0.879508376121521, 0.0, 0.0]]]}